{
  "card_id": "currency_futures_pairing_strategy",
  "type": "merged_concept",
  "canonical_term": "Currency Futures Pairing Strategy",
  "aliases": [
    "DXY Pairing Strategy",
    "dxy pairing strategy",
    "Strongest vs Weakest Currency Pairing",
    "strongest vs weakest currency pairing"
  ],
  "school": "Order Flow",
  "definition": "A forex/currency-futures selection framework that pairs the strongest currency with the weakest to maximize trend expansion. When DXY trends, pair it with the opposite-direction extreme; when DXY consolidates, pair two non-dollar currencies with opposing directional bias to isolate the highest-probability expansion pair.",
  "identification_rules": [
    "Assess DXY first: classify it as bullish trending, bearish trending, or consolidating.",
    "If DXY is bullish trending, identify the most bearish foreign currency and pair them (e.g., DXY + weak EUR → trade EUR/USD short).",
    "If DXY is bearish trending, identify the strongest bullish foreign currency and pair them (e.g., DXY + strong JPY → trade USD/JPY short).",
    "If DXY is consolidating, ignore the dollar and pair the strongest non-dollar currency with the weakest non-dollar currency (e.g., bullish EUR vs. bearish JPY → EUR/JPY long).",
    "If all currencies trend the same direction with no opposing extreme, pair the trending currency with a consolidating one (acceptable but weaker expansion).",
    "For futures-only traders: when DXY trends, simply trade the single opposite-direction currency future that is strongest/weakest; when DXY consolidates, long the strongest and short the weakest as separate trades."
  ],
  "trading_implication": "Used to filter the forex/currency-futures universe down to the single highest-probability pair for expansion. Pairing strong vs. weak produces the cleanest directional trends; pairing trend vs. consolidation produces weaker trends. The framework determines which symbol to apply entry models on, ensuring the chosen instrument has maximum directional fuel from both legs of the pair.",
  "common_mistakes": [
    "Pairing two trending currencies of the same strength, which leaves a consolidation rather than a trend.",
    "Pairing a strong or weak currency with a consolidating one when a true opposite-extreme is available — produces a weaker trend than the optimal pairing.",
    "Continuing to pair with the dollar when DXY itself is consolidating instead of switching to non-dollar cross pairs."
  ],
  "related_concepts": [],
  "illustrated_by_cases": [],
  "source_cards": [
    {
      "video_id": "HrjYoxAUb3s",
      "original_card_id": "HrjYoxAUb3s_concept_currency_futures_pairing_strategy",
      "segment_ids": [
        "seg_006",
        "seg_007",
        "seg_008",
        "seg_009"
      ],
      "time_range": [
        193.68,
        403.12
      ],
      "extraction_confidence": "high"
    }
  ],
  "stats": {
    "source_count": 1,
    "source_videos": 1,
    "high_confidence_sources": 1,
    "medium_confidence_sources": 0,
    "low_confidence_sources": 0
  },
  "merge_strategy": "single_source",
  "merged_at": "2026-05-17T18:09:12.075305Z",
  "merge_model": null,
  "review_status": "pending",
  "notes": null,
  "warnings": [],
  "merge_notes": null,
  "error": null,
  "_embedding": [
    0.0087755611166358,
    0.0860072523355484,
    -0.22074076533317566,
    -0.027939939871430397,
    0.03240314871072769,
    -0.03590823709964752,
    -0.022679729387164116,
    -0.042693428695201874,
    0.025852298364043236,
    -0.030690396204590797,
    -0.004695080686360598,
    0.006180994678288698,
    0.06345649063587189,
    -0.015894388779997826,
    0.03885090723633766,
    0.003373619867488742,
    -0.0016366384224966168,
    -0.04123161733150482,
    0.013298562727868557,
    0.030165206640958786,
    -0.028881466016173363,
    -0.0006458810530602932,
    -0.01857520081102848,
    -0.021531132981181145,
    0.04778406023979187,
    -0.025328336283564568,
    0.008323057554662228,
    -0.05412352457642555,
    -0.037302739918231964,
    0.011950272135436535,
    0.02127433381974697,
    0.0035685545299202204,
    0.02842153050005436,
    -0.00968780554831028,
    -0.0808182954788208,
    -0.0371425598859787,
    0.035967130213975906,
    -0.0016021027695387602,
    0.02816212736070156,
    -0.06412757188081741,
    0.005675774998962879,
    0.039140090346336365,
    0.055209334939718246,
    -0.035424426198005676,
    0.05232183635234833,
    -0.003718468826264143,
    0.03580106422305107,
    0.0003357379464432597,
    0.047648388892412186,
    -0.04286778345704079,
    0.004359347280114889,
    0.061505429446697235,
    0.05737925320863724,
    -0.030056092888116837,
    0.04968560114502907,
    0.04236309230327606,
    0.0012888303026556969,
    0.050790347158908844,
    0.009183753281831741,
    -0.03855568915605545,
    0.06351935863494873,
    0.045356426388025284,
    -0.012223693542182446,
    0.04801627993583679,
    0.0611150898039341,
    -0.032675545662641525,
    -0.03710755333304405,
    0.056280508637428284,
    0.0386354885995388,
    -0.061662495136260986,
    0.03641936928033829,
    -0.01761161908507347,
    0.03965424373745918,
    0.018649576231837273,
    -0.023731140419840813,
    0.002942688064649701,
    -0.038765132427215576,
    -0.02104121819138527,
    0.0008911203476600349,
    -0.00034408076317049563,
    0.0066076768562197685,
    -5.975703243166208e-05,
    0.08698002249002457,
    0.01586119271814823,
    0.05990360677242279,
    0.007205731701105833,
    0.012265852652490139,
    -0.0068391356617212296,
    -0.024330364540219307,
    0.06792367994785309,
    -0.01847122795879841,
    -0.009125340729951859,
    0.033346664160490036,
    0.029739312827587128,
    -0.07816648483276367,
    0.03205593302845955,
    -0.018336201086640358,
    0.024405864998698235,
    -0.016832547262310982,
    -0.057371772825717926,
    -0.024212220683693886,
    -0.0025422482285648584,
    -0.01251512486487627,
    -0.004178971983492374,
    0.014841589145362377,
    0.024184318259358406,
    0.014841075986623764,
    0.044876184314489365,
    -0.0296177938580513,
    -0.03344635292887688,
    -0.06834586709737778,
    0.05426837503910065,
    -0.019638463854789734,
    -0.005988879129290581,
    0.05020206421613693,
    0.007085091900080442,
    0.0029959138482809067,
    -0.013429579325020313,
    -0.004682254046201706,
    0.059572573751211166,
    0.02303476817905903,
    -0.014594328589737415,
    0.01089019700884819,
    0.062065787613391876,
    0.00016992661403492093,
    0.045141708105802536,
    -0.05614655092358589,
    -0.01603247970342636,
    0.04641122370958328,
    -0.0509624108672142,
    0.01107837911695242,
    -0.010720835067331791,
    0.043256763368844986,
    -0.03046329692006111,
    -0.021330228075385094,
    0.07475898414850235,
    -0.010832086205482483,
    -0.0021623356733471155,
    0.031249238178133965,
    0.03501179814338684,
    0.05432684347033501,
    -0.057377442717552185,
    0.0013738312991335988,
    -0.027064906433224678,
    -0.039443645626306534,
    -0.04368238151073456,
    0.03477105870842934,
    -0.05273684114217758,
    -0.024874839931726456,
    0.005402128212153912,
    -0.004372533410787582,
    0.03651255741715431,
    -0.021702194586396217,
    0.01713908277451992,
    0.05572746694087982,
    -0.011435096152126789,
    0.040321774780750275,
    -0.03522157296538353,
    0.02015847899019718,
    -0.010233642533421516,
    0.05076463147997856,
    -0.006617169361561537,
    0.003405494848266244,
    0.026338350027799606,
    -0.04429156705737114,
    -0.07456213235855103,
    0.03743749111890793,
    0.037302836775779724,
    0.035460732877254486,
    0.07201434671878815,
    -0.05408833548426628,
    -0.04323636367917061,
    -0.010562040843069553,
    -0.024974972009658813,
    0.04933870956301689,
    0.02429129183292389,
    0.06735429912805557,
    -0.012096337042748928,
    0.0045669227838516235,
    -0.038318436592817307,
    -0.005491940770298243,
    -0.010404546745121479,
    0.05563226342201233,
    0.034973084926605225,
    -0.01406775787472725,
    -0.012023372575640678,
    0.03906244784593582,
    0.01338974293321371,
    -0.0257148128002882,
    -0.0315697081387043,
    0.039442017674446106,
    0.021298399195075035,
    -0.0572570376098156,
    -0.013778521679341793,
    -0.048550933599472046,
    -0.057194486260414124,
    0.021273255348205566,
    -0.0013953986344859004,
    0.004193630535155535,
    -0.03381771594285965,
    -0.05154455080628395,
    -0.036598652601242065,
    0.005339157301932573,
    0.0022340244613587856,
    -0.03394945710897446,
    0.02316458895802498,
    -0.06144079193472862,
    0.07586874812841415,
    -0.005406356416642666,
    0.008868386037647724,
    0.05418277904391289,
    0.00081318971933797,
    -0.018512403592467308,
    0.009096309542655945,
    -0.023820869624614716,
    -0.04428563639521599,
    0.03312009572982788,
    0.018352771177887917,
    -0.050983864814043045,
    0.002421105746179819,
    0.0019064175430685282,
    -0.013396439142525196,
    0.014341382309794426,
    0.039758823812007904,
    0.025703391060233116,
    -0.022588010877370834,
    -0.025748085230588913,
    0.0007684375159442425,
    -0.0364900641143322,
    0.02126189135015011,
    -0.020825115963816643,
    -0.08048504590988159,
    0.009907751344144344,
    0.00197759666480124,
    0.017978016287088394,
    0.009588435292243958,
    0.03570600599050522,
    0.07047049701213837,
    0.003476759186014533,
    0.03071637637913227,
    -0.022220924496650696,
    0.03579079732298851,
    -0.03763530030846596,
    -0.0028464316856116056,
    -0.033851198852062225,
    0.028318345546722412,
    0.020487315952777863,
    0.004889547359198332,
    0.012354796752333641,
    0.047266993671655655,
    0.03337794542312622,
    -0.007849602960050106,
    -0.017716385424137115,
    -0.015427914448082447,
    0.014524994418025017,
    -0.0066507309675216675,
    -0.06684184074401855,
    0.0352364256978035,
    0.006689679343253374,
    -0.01408424973487854,
    0.01109555084258318,
    0.02145410142838955,
    0.08078513294458389,
    -0.06542618572711945,
    -0.007139516528695822,
    -0.017170973122119904,
    -0.011565635912120342,
    -0.02590976282954216,
    -0.02468821033835411,
    -0.004597755614668131,
    0.01718926429748535,
    0.024515189230442047,
    0.009251774288713932,
    0.037454281002283096,
    -0.003737922292202711,
    -0.006657555233687162,
    0.02433379739522934,
    -0.044956404715776443,
    -0.05220639705657959,
    0.05114065110683441,
    0.008048517629504204,
    -0.027525687590241432,
    -0.04167791083455086,
    0.018610568717122078,
    -0.016613293439149857,
    0.04967939108610153,
    0.0672626867890358,
    0.0617867186665535,
    0.01166599802672863,
    0.034342315047979355,
    -0.009843426756560802,
    -0.008276521228253841,
    -0.005411812569946051,
    0.012261766009032726,
    -0.020826658234000206,
    0.021712318062782288,
    0.09670057147741318,
    -0.02542158216238022,
    0.018572237342596054,
    -0.04361340403556824,
    0.03330571949481964,
    0.004640348721295595,
    0.07978060841560364,
    0.054176993668079376,
    0.011311952024698257,
    0.017873192206025124,
    0.003654148895293474,
    -0.062000878155231476,
    -0.0005692399572581053,
    -0.06248358264565468,
    0.02250092104077339,
    0.010932741686701775,
    -0.058711398392915726,
    -0.005486946552991867,
    -0.06260666996240616,
    0.032944757491350174,
    0.05594902113080025,
    0.04754973202943802,
    0.04149923101067543,
    -0.04698604717850685,
    0.02241957001388073,
    -0.02298695780336857,
    0.01183499488979578,
    -0.07450149208307266,
    0.016742568463087082,
    0.04759441316127777,
    -0.03379452973604202,
    0.026833949610590935,
    -0.03553704172372818,
    0.01562969759106636,
    0.009302335791289806,
    0.04454835504293442,
    0.020840194076299667,
    -0.023025967180728912,
    -0.05105389654636383,
    0.004521559923887253,
    -0.0013596181524917483,
    0.013605744577944279,
    0.016053572297096252,
    0.059768564999103546,
    0.05949942767620087,
    -0.02554827183485031,
    0.051123905926942825,
    -0.043306224048137665,
    0.02394925244152546,
    -0.002325488720089197,
    -0.027218101546168327,
    0.01685936748981476,
    0.039593957364559174,
    0.007150488905608654,
    -0.015965385362505913,
    -0.0035625624004751444,
    0.011893962509930134,
    -0.0006792223430238664,
    0.03598562628030777,
    -0.012747556902468204,
    0.05785268545150757,
    0.01305296178907156,
    0.036472853273153305,
    0.013532190583646297,
    0.050925735384225845,
    -0.0046019055880606174,
    -0.035683680325746536,
    -0.0042491210624575615,
    -0.02640734799206257,
    0.009920693002641201,
    0.047762200236320496,
    -0.03105871006846428,
    -0.0019374334951862693,
    -0.012872208841145039,
    -0.04716116562485695,
    -0.006186842452734709,
    -0.032819852232933044,
    0.07375013083219528,
    -0.024477733299136162,
    -0.014561504125595093,
    -0.08411721140146255,
    -0.007916668429970741,
    0.0043775225058197975,
    0.02646544575691223,
    0.01641513779759407,
    0.007181794382631779,
    0.030841078609228134,
    0.03646856173872948,
    0.008047591894865036,
    -0.004978544544428587,
    -0.017239879816770554,
    -0.06873318552970886,
    -0.022167569026350975,
    0.012967638671398163,
    0.0317615307867527,
    0.006086848676204681,
    -0.003046291181817651,
    0.03273511305451393,
    0.03731846809387207,
    -0.015558316372334957,
    0.042209330946207047,
    0.03742305561900139,
    -0.02807418815791607,
    -0.008974798955023289,
    -0.07183124870061874,
    -0.0849975124001503,
    -0.008787037804722786,
    -0.06280673295259476,
    -0.009230360388755798,
    -0.0032994693610817194,
    -0.061591774225234985,
    -0.05870889127254486,
    0.037604302167892456,
    -0.021252498030662537,
    0.043046142905950546,
    0.06751649081707001,
    -0.03181174769997597,
    -0.05948114022612572,
    0.01714491844177246,
    0.022134125232696533,
    0.05508079379796982,
    -0.007369800005108118,
    -0.00626446632668376,
    0.014529543928802013,
    0.05561550334095955,
    0.04932411015033722,
    0.00011274561256868765,
    -0.0087564243003726,
    -0.007910363376140594,
    0.038424160331487656,
    0.043692559003829956,
    0.07113552838563919,
    -0.00403254060074687,
    -0.052573371678590775,
    0.01313806138932705,
    0.019618911668658257,
    0.011665591038763523,
    -0.041598815470933914,
    -0.026189012452960014,
    -0.024512382224202156,
    0.018603650853037834,
    -0.0034785533789545298,
    -0.03252384811639786,
    0.06921917200088501,
    0.03790783882141113,
    -0.039546649903059006,
    -0.049080099910497665,
    0.012512777000665665,
    0.0048284814693033695,
    0.07493767142295837,
    0.06722499430179596,
    -0.02939726784825325,
    -0.03805823251605034,
    0.00916563905775547,
    -0.012813465669751167,
    0.02647627703845501,
    0.032118164002895355,
    0.03262331709265709,
    0.07030503451824188,
    -0.04520806297659874,
    0.019104257225990295,
    0.0023469580337405205,
    0.024246549233794212,
    0.020281299948692322,
    -0.001649380661547184,
    0.03230524808168411,
    -0.06157386302947998,
    0.015274109318852425,
    0.01917308010160923,
    -0.017229275777935982,
    0.010156882926821709,
    -0.027351662516593933,
    -0.008028898388147354,
    0.059980519115924835,
    -0.06311461329460144,
    -0.023225747048854828,
    0.038655754178762436,
    0.009931826032698154,
    -0.007134812884032726,
    -0.020704664289951324,
    -0.005530737806111574,
    -0.029202649369835854,
    0.028660856187343597,
    -0.003130682511255145,
    -0.004430865403264761,
    0.010470540262758732,
    0.023807428777217865,
    -0.00640680780634284,
    -0.046261582523584366,
    0.003093849401921034,
    0.006717997137457132,
    -0.058388177305459976,
    0.008385798893868923,
    -0.011480815708637238,
    0.032362550497055054,
    0.02404230833053589,
    0.015945402905344963,
    -0.034511856734752655,
    -0.05122756212949753,
    -0.028735367581248283,
    0.007919016294181347,
    0.013512597419321537,
    -0.005122508388012648,
    -0.021842550486326218,
    0.015882914885878563,
    0.02825554646551609,
    -0.003827087115496397,
    -0.0263274684548378,
    0.0703219547867775,
    -0.03403913229703903,
    0.05842355266213417,
    -0.0826568529009819,
    -0.015180660411715508,
    0.019588865339756012,
    -0.046337880194187164,
    0.003132645972073078,
    0.05877524986863136,
    0.01716623455286026,
    0.04227075353264809,
    -0.05845523998141289,
    0.015599710866808891,
    0.008892683312296867,
    0.003989342134445906,
    -0.011457999236881733,
    0.005355179775506258,
    -0.00015123894263524562,
    -0.02617323026061058,
    0.0017664753831923008,
    -0.022189166396856308,
    -0.006922746077179909,
    -0.040804021060466766,
    -0.012284010648727417,
    0.053900718688964844,
    -0.011544433422386646,
    0.033862560987472534,
    1.5003021871962119e-05,
    -0.006373984273523092,
    0.02205917052924633,
    0.00432251300662756,
    -0.009640088304877281,
    -0.04319855570793152,
    0.03938969597220421,
    -0.010962182655930519,
    0.03580920025706291,
    0.00985407829284668,
    0.047573354095220566,
    0.000584377849008888,
    0.012832424603402615,
    -0.029262151569128036,
    -0.010012619197368622,
    -0.000842743378598243,
    0.007037228439003229,
    -0.0018157226732000709,
    -0.05091722682118416,
    0.0015711612068116665,
    -0.053464457392692566,
    -0.02083008922636509,
    -0.05604735389351845,
    0.05445617437362671,
    -0.0441097691655159,
    -0.006677736062556505,
    -0.026542549952864647,
    -0.04283873364329338,
    -0.004448287189006805,
    -0.0029698458965867758,
    -0.005250249989330769,
    0.047434985637664795,
    0.08679986000061035,
    0.05625172331929207,
    -0.03653670847415924,
    0.017979849129915237,
    -0.010347690433263779,
    0.02679079957306385,
    0.041186969727277756,
    -0.02129208855330944,
    -0.06072001904249191,
    -0.04292285814881325,
    0.011022075079381466,
    0.0019460826879367232,
    -0.01863984577357769,
    -0.003224035259336233,
    -0.008263252675533295,
    -0.05860817804932594,
    -0.02356010675430298,
    -0.015972504392266273,
    -0.03244607895612717,
    0.009049125015735626,
    0.057999517768621445,
    -0.04869573563337326,
    0.021250152960419655,
    -0.014732971787452698,
    -0.05569970980286598,
    0.005861734040081501,
    -0.06612426787614822,
    -0.014875232242047787,
    0.024698922410607338,
    0.0023398599587380886,
    -0.048897113651037216,
    0.012147420085966587,
    0.041518911719322205,
    -0.0018351629842072725,
    -0.043645862489938736,
    -0.07281828671693802,
    -0.01781480386853218,
    -0.059505440294742584,
    0.03516312316060066,
    0.04535653814673424,
    -0.05915430933237076,
    -0.0017030105227604508,
    0.06755751371383667,
    0.004477126058191061,
    0.06429154425859451,
    -0.011263291351497173,
    0.0013616279466077685,
    0.011996166780591011,
    0.0026284619234502316,
    0.017163805663585663,
    -0.046324748545885086,
    0.03346097096800804,
    -0.027575569227337837,
    0.042771175503730774,
    0.004727264400571585,
    -0.026718826964497566,
    0.005299786571413279,
    -0.030705485492944717,
    -0.0379231795668602,
    0.023341596126556396,
    -0.04165360704064369,
    0.05450848862528801,
    0.017709780484437943,
    -0.024406537413597107,
    -0.08968530595302582,
    0.010740083642303944,
    0.02834571897983551,
    -0.03269408643245697,
    0.006970955990254879,
    -0.09120345860719681,
    -0.04482432082295418,
    -0.06183946505188942,
    0.024020368233323097,
    -0.05464896187186241,
    0.03229408338665962,
    -0.0008802064112387598,
    0.0389920137822628,
    0.029621729627251625,
    0.010849683545529842,
    -0.007922322489321232,
    0.013727975077927113,
    0.0606766976416111,
    -0.03483472019433975,
    0.010806399397552013,
    0.06999880075454712,
    0.03404676169157028,
    -0.0341288186609745,
    0.05033358559012413,
    0.054374631494283676,
    0.018283870071172714,
    0.0021636553574353456,
    -0.007006403524428606,
    0.024518286809325218,
    0.05151042714715004,
    -0.04856907203793526,
    -0.04004208371043205,
    -0.03140868619084358,
    0.010075202211737633,
    -0.004965577740222216,
    -0.04877227544784546,
    0.006083168089389801,
    0.009461618028581142,
    -0.01705212891101837,
    -0.020544029772281647,
    -0.02126871421933174,
    -0.08375978469848633,
    -0.03486908972263336,
    0.04030205309391022,
    -0.004204713273793459,
    -0.03861602768301964,
    -0.029591642320156097,
    0.03246282413601875,
    -0.007001038175076246,
    0.016264453530311584,
    0.02095824107527733,
    -0.02238357625901699,
    -0.034865789115428925,
    0.013472631573677063,
    0.003112747333943844,
    0.02767803706228733,
    -0.04943539947271347,
    -0.037859104573726654,
    0.010681933723390102,
    0.0341414138674736,
    -0.02071576751768589,
    -0.01609267108142376,
    -0.03828105330467224,
    -0.038770418614149094,
    -0.042146578431129456,
    0.02265622466802597,
    -0.0010310420766472816,
    -0.02629602700471878,
    0.030784297734498978,
    -0.011848356574773788,
    0.0002866380091290921,
    -0.05250764265656471,
    0.05394954979419708,
    -0.005053489003330469,
    0.0259585902094841,
    -0.008131013251841068,
    0.03733913600444794,
    -0.023908309638500214,
    -0.00018572263070382178,
    0.04191949963569641,
    -0.020014304667711258,
    0.006141066551208496,
    -0.03208199515938759,
    0.026640577241778374,
    -0.00960555300116539,
    0.016263877972960472,
    0.012882660143077374,
    -0.0026586337480694056,
    0.011457309126853943,
    0.012059899978339672,
    -0.08893705159425735,
    -0.0206182599067688,
    0.031848203390836716,
    0.03604387864470482,
    -0.011646618135273457,
    -0.03214329481124878,
    -0.055933959782123566,
    -0.02869747392833233,
    -0.03178337588906288,
    0.019019953906536102,
    -0.020613033324480057,
    -0.0004547084972728044,
    -0.0015645214589312673,
    0.006803466938436031,
    -0.02174498327076435,
    -0.03217659890651703,
    0.06669048219919205,
    -0.011944788508117199,
    0.030112138018012047,
    -0.04283834248781204,
    -0.00014661923341918737,
    -0.02890881896018982,
    0.017149806022644043,
    -0.04440448805689812,
    0.015513607300817966,
    -0.025087324902415276,
    -0.024288693442940712,
    -0.007731742691248655,
    -0.02973715029656887,
    0.0027978369034826756,
    0.032747380435466766,
    0.031133465468883514,
    -0.008733746595680714,
    0.021750207990407944,
    -0.011110718362033367,
    0.0018462111474946141,
    -0.035852111876010895,
    -0.009123680181801319,
    0.04199711233377457,
    -0.02217038907110691,
    0.0008670928655192256,
    0.12046685814857483,
    0.013155961409211159,
    0.04196176305413246,
    -0.03531820699572563,
    0.03974615037441254,
    -0.029774202033877373,
    -0.014221683144569397,
    -0.025372624397277832,
    -0.07566700130701065,
    -0.02842116355895996
  ],
  "_embedding_model": "nomic-ai/nomic-embed-text-v1.5"
}
